autouniq/__init__.py
autouniq/case.py
autouniq/collection_framework.py
autouniq/core.py
autouniq/parcer.py
autouniq/test_new.py
autouniq/test_old.py
autouniq-0.0.5.dist-info/METADATA
autouniq-0.0.5.dist-info/WHEEL
autouniq-0.0.5.dist-info/licenses/License
autouniq-0.0.5.dist-info/RECORD
